LICENSE.txt
MANIFEST.in
pottymouth.py
profile.py
readme.html
setup.py
tests.py
web.py
PottyMouth.egg-info/PKG-INFO
PottyMouth.egg-info/SOURCES.txt
PottyMouth.egg-info/dependency_links.txt
PottyMouth.egg-info/top_level.txt
debian/changelog
debian/control
debian/copyright
debian/pyversions
debian/rules