Metadata-Version: 1.1
Name: PottyMouth
Version: 2.2.1
Summary: transform unstructured, untrusted text to safe, valid XHTML
Home-page: http://glyphobet.net/pottymouth
Author: Matt Chisholm
Author-email: matt@theory.org
License: BSD License
Download-URL: http://glyphobet.net/pottymouth/dist/
Keywords: wiki
Platform: All
Classifier: Development Status :: 5 - Production/Stable
Classifier: Intended Audience :: Developers
Classifier: License :: OSI Approved :: BSD License
Classifier: Operating System :: OS Independent
Classifier: Environment :: Web Environment
Classifier: Topic :: Internet :: WWW/HTTP :: Dynamic Content :: Message Boards
Classifier: Topic :: Internet :: WWW/HTTP :: Dynamic Content :: News/Diary
Classifier: Programming Language :: Python :: 2.6
Classifier: Programming Language :: Python :: 2.7
